AUTHORS.rst
CONTRIBUTING.rst
HISTORY.rst
LICENSE
MANIFEST.in
README.rst
setup.cfg
setup.py
docs/Makefile
docs/authors.rst
docs/conf.py
docs/contributing.rst
docs/history.rst
docs/index.rst
docs/installation.rst
docs/make.bat
docs/readme.rst
docs/usage.rst
fsdesign/__init__.py
fsdesign/cli.py
fsdesign/factor.py
fsdesign/fsdesign.py
fsdesign.egg-info/PKG-INFO
fsdesign.egg-info/SOURCES.txt
fsdesign.egg-info/dependency_links.txt
fsdesign.egg-info/entry_points.txt
fsdesign.egg-info/not-zip-safe
fsdesign.egg-info/requires.txt
fsdesign.egg-info/top_level.txt
tests/__init__.py
tests/test_fsdesign.py
tests/data/.~lock.output.csv#
tests/data/Prueba1.txt
tests/data/factors.csv
tests/data/output.csv
tests/data/output1.csv
tests/data/output2.csv
tests/data/template.txt