Metadata-Version: 1.1
Name: fsdesign
Version: 0.1.4
Summary: Python package for Factorial Survey Design
Home-page: https://github.com/bertucho/fsdesign
Author: Alberto Egido
Author-email: UNKNOWN
License: MIT license
Keywords: fsdesign
Platform: UNKNOWN
Classifier: Development Status :: 2 - Pre-Alpha
Classifier: Intended Audience :: Developers
Classifier: License :: OSI Approved :: MIT License
Classifier: Natural Language :: English
Classifier: Programming Language :: Python :: 3
Classifier: Programming Language :: Python :: 3.4
Classifier: Programming Language :: Python :: 3.5
Classifier: Programming Language :: Python :: 3.6
